{
  "rules": {
    "isAllUpperCase": {
      "weight": 0.905241935483871,
      "threshold": 0.5
    },
    "startsWithNumberOrBracket": {
      "weight": 0,
      "threshold": 0.5
    },
    "containsYear": {
      "weight": -0.18346774193548387,
      "threshold": 0.5
    },
    "lengthRange": {
      "weight": 0.46370967741935487,
      "threshold": 0.5,
      "minLength": 3,
      "maxLength": 50
    },
    "positionRatio": {
      "weight": 0.1875,
      "threshold": 0.5
    },
    "wordCount": {
      "weight": 0.344758064516129,
      "threshold": 0.5,
      "maxWords": 8
    },
    "hasColon": {
      "weight": -0.0846774193548387,
      "threshold": 0.5
    },
    "matchesPublicationPattern": {
      "weight": 1,
      "threshold": 0.5
    },
    "endsWithPeriodOrPercent": {
      "weight": 0,
      "threshold": 0.5
    },
    "isShort": {
      "weight": 0,
      "threshold": 0.5
    },
    "indentationLevel": {
      "weight": 0,
      "threshold": 0.5
    }
  },
  "trained": true
}